README.rst
setup.py
distro_tutorial/__init__.py
distro_tutorial.egg-info/PKG-INFO
distro_tutorial.egg-info/SOURCES.txt
distro_tutorial.egg-info/dependency_links.txt
distro_tutorial.egg-info/entry_points.txt
distro_tutorial.egg-info/top_level.txt