Metadata-Version: 1.1
Name: distro-tutorial
Version: 0.0.3
Summary: A sample Python distribution project
Home-page: https://github.com/splanger/python_distro_tutorial.git
Author: Yuri Kroz
Author-email: splanger@gmail.com
License: Apache Software License
Keywords: sample setuptools development tutorial packaging
Platform: UNKNOWN
Classifier: Development Status :: 4 - Beta
Classifier: Intended Audience :: Developers
Classifier: Topic :: Software Development :: Build Tools
Classifier: License :: OSI Approved :: Apache Software License
Classifier: Programming Language :: Python :: 2
Classifier: Programming Language :: Python :: 2.6
Classifier: Programming Language :: Python :: 2.7
